klose/__init__.py
klose/config.py
klose/configuration_dev.json
klose/configuration_pro.json
klose/conf/dev.env
klose/conf/pro.env
klose/core/__init__.py
klose/core/configuration.py
klose/core/ws_connection_manager.py
klose/core/msg/__init__.py
klose/core/msg/dingtalk.py
klose/core/msg/mail.py
klose/core/msg/notification.py
klose/core/msg/wss_msg.py
klose/enums/DatabaseEnum.py
klose/enums/GconfigEnum.py
klose/enums/NoticeEnum.py
klose/enums/OperationEnum.py
klose/enums/OssEnum.py
klose/enums/RequestBodyEnum.py
klose/enums/RequestTypeEnum.py
klose/enums/__init__.py
klose/excpetions/AuthException.py
klose/excpetions/ParamsException.py
klose/excpetions/RedisException.py
klose/excpetions/RequestException.py
klose/excpetions/RpcError.py
klose/excpetions/__init__.py
klose/excpetions/convert/ConvertException.py
klose/excpetions/convert/GenerateException.py
klose/excpetions/convert/__init__.py
klose/excpetions/database/DbException.py
klose/excpetions/database/__init__.py
klose/model/__init__.py
klose/model/basic.py
klose/model/operation_log.py
klose/request/__init__.py
klose/request/encoder.py
klose/request/fatcory.py
klose/request/request_pb2.py
klose/request/request_pb2_grpc.py
klose/scripts/wait-for-it.sh
klose/templates/report.html
klose/templates/reset_password.html
klose/templates/markdown/test_report.md
klose/templates/markdown/test_report_bak.md
klose/third_party/Redis.py
klose/third_party/__init__.py
klose/third_party/auth.py
klose/third_party/sql.py
klose/third_party/oss/__init__.py
klose/third_party/oss/aliyun.py
klose/third_party/oss/files.py
klose/third_party/oss/qiniu.py
klose/third_party/oss/tencent.py
klose/utils/AsyncHttpClient.py
klose/utils/GrpcClient.py
klose/utils/HttpClient.py
klose/utils/RedisManager.py
klose/utils/__init__.py
klose/utils/case_logger.py
klose/utils/client.py
klose/utils/context.py
klose/utils/decorator.py
klose/utils/des.py
klose/utils/etcd.py
klose/utils/gconfig_parser.py
klose/utils/json_compare.py
klose/utils/logger.py
klose-0.0.69.dist-info/LICENSE
klose-0.0.69.dist-info/METADATA
klose-0.0.69.dist-info/WHEEL
klose-0.0.69.dist-info/top_level.txt
klose-0.0.69.dist-info/RECORD
