Metadata-Version: 2.1
Name: klose
Version: 0.0.69
Summary: pity internal package
Home-page: https://github.com/wuranxu/klose
Author: miro
Author-email: 619434176@qq.com
License: UNKNOWN
Platform: UNKNOWN
Classifier: Programming Language :: Python :: 3
Classifier: License :: OSI Approved :: MIT License
Classifier: Operating System :: OS Independent
License-File: LICENSE
Requires-Dist: setuptools (>=42)
Requires-Dist: wheel
Requires-Dist: pyjwt
Requires-Dist: pydantic[email]
Requires-Dist: sqlalchemy
Requires-Dist: aiohttp
Requires-Dist: awaits
Requires-Dist: grpc-requests
Requires-Dist: grpcio (==1.45.0)
Requires-Dist: protobuf (==3.19.4)
Requires-Dist: loguru
Requires-Dist: redis (~=3.5.3)
Requires-Dist: redis-py-cluster
Requires-Dist: starlette
Requires-Dist: fastapi
Requires-Dist: redlock
Requires-Dist: pyDes
Requires-Dist: aioetcd3
Requires-Dist: pyyaml
Requires-Dist: requests
Requires-Dist: qiniu (~=7.6.0)
Requires-Dist: cos-python-sdk-v5
Requires-Dist: pydantic[dotenv]
Requires-Dist: pydantic
Requires-Dist: jinja2
Requires-Dist: aiomysql
Requires-Dist: pymysql
Requires-Dist: oss2
Requires-Dist: mysql-connector-python (>=8.0.26)
